{
	"students": [
		{ "id": 1, "name": "Philip", "counts": 2, "group": "a" },
		{ "id": 2, "name": "Darrell", "counts": 5, "group": "b" },
		{ "id": 3, "name": "Guest", "counts": 0, "group": null },
		{ "id": 4, "name": "Cody", "counts": 1, "group": "c" },
		{ "id": 5, "name": "Guest", "counts": 0, "group": null },
		{ "id": 6, "name": "Guest", "counts": 0, "group": null },
		{ "id": 7, "name": "Bessie", "counts": 2, "group": "a" },
		{ "id": 8, "name": "Wendy", "counts": 3, "group": "a" },
		{ "id": 9, "name": "Guest", "counts": 0, "group": null },
		{ "id": 10, "name": "Esther", "counts": 1, "group": "b" },
		{ "id": 11, "name": "Guest", "counts": 0, "group": null },
		{ "id": 12, "name": "Gloria", "counts": 0, "group": "c" },
		{ "id": 13, "name": "Guest", "counts": 0, "group": null },
		{ "id": 14, "name": "Lee", "counts": 0, "group": "b" },
		{ "id": 15, "name": "Guest", "counts": 0, "group": null },
		{ "id": 16, "name": "Ann", "counts": 0, "group": "b" },
		{ "id": 17, "name": "Jacob", "counts": 1, "group": "b" },
		{ "id": 18, "name": "Calvin", "counts": 0, "group": "a" },
		{ "id": 19, "name": "Guest", "counts": 0, "group": null },
		{ "id": 20, "name": "Joe", "counts": 0, "group": "c" }
	]
}
